django_pre_post/__init__.py
django_pre_post/admin.py
django_pre_post/forms.py
django_pre_post/models.py
django_pre_post/serializers.py
django_pre_post/settings.py
django_pre_post/urls.py
django_pre_post/util.py
django_pre_post/views.py
django_pre_post/viewsets.py
django_pre_post/wsgi.py
django_pre_post/migrations/0001_initial.py
django_pre_post/migrations/0002_auto_20180402_2043.py
django_pre_post/migrations/__init__.py
django_pre_post/templates/base.html
django_pre_post/templates/django_pre_post/fill_in_the_blank.html
django_pre_post/templates/django_pre_post/frameless_questionnaire.html
django_pre_post/templates/django_pre_post/frameless_success.html
django_pre_post/templates/django_pre_post/multiple_choice.html
django_pre_post/templates/django_pre_post/numeric.html
django_pre_post/templates/django_pre_post/open_ended.html
django_pre_post/templates/django_pre_post/questionnaire_form.html
django_pre_post/templates/django_pre_post/rank.html
django_pre_post/templates/django_pre_post/successful_post.html
preerpost-0.0.92.dist-info/LICENSE
preerpost-0.0.92.dist-info/METADATA
preerpost-0.0.92.dist-info/WHEEL
preerpost-0.0.92.dist-info/top_level.txt
preerpost-0.0.92.dist-info/RECORD
