Metadata-Version: 2.1
Name: preerpost
Version: 0.0.92
Summary: This package provides a framework for surveys and questionnaires
Home-page: UNKNOWN
Author: Sumedh Walujkar
Author-email: sumedh@umich.edu
License: UNKNOWN
Keywords: test,pre-post,questionnaire,survey
Platform: UNKNOWN
